nlp_time/__init__.py
nlp_time/__version__.py
nlp_time/core.py
nlp_time/utils.py
nlp_time-0.1.14.dist-info/LICENSE
nlp_time-0.1.14.dist-info/METADATA
nlp_time-0.1.14.dist-info/WHEEL
nlp_time-0.1.14.dist-info/top_level.txt
nlp_time-0.1.14.dist-info/RECORD
