Metadata-Version: 2.1
Name: nlp-time
Version: 0.1.14
Summary: Chinese to time, time to Chinese.
Home-page: https://github.com/holbos-deng/nlp_time
Author: Holbos Deng
Author-email: 2292861292@qq.com
License: MIT
Platform: UNKNOWN
Classifier: License :: OSI Approved :: MIT License
Classifier: Programming Language :: Python
Classifier: Programming Language :: Python :: 3
Classifier: Programming Language :: Python :: 3.7
Classifier: Programming Language :: Python :: 3.8
Classifier: Programming Language :: Python :: 3.9
Classifier: Programming Language :: Python :: 3.10
Classifier: Programming Language :: Python :: Implementation :: CPython
Classifier: Programming Language :: Python :: Implementation :: PyPy
Requires-Python: >=3.7.0
Requires-Dist: jionlp (==1.3.58)
Requires-Dist: python-dateutil
